{"document_tone":{"tone_categories":[{"tones":[{"score":0.016396,"tone_id":"anger","tone_name":"Anger"},{"score":0.023864,"tone_id":"disgust","tone_name":"Disgust"},{"score":0.056441,"tone_id":"fear","tone_name":"Fear"},{"score":0.811474,"tone_id":"joy","tone_name":"Joy"},{"score":0.106078,"tone_id":"sadness","tone_name":"Sadness"}],"category_id":"emotion_tone","category_name":"Emotion Tone"}]},"sentences_tone":[{"sentence_id":0,"text":"Shall I compare thee to a summer's day?","input_from":0,"input_to":39,"tone_categories":[{"tones":[{"score":0.060671,"tone_id":"anger","tone_name":"Anger"},{"score":0.030574,"tone_id":"disgust","tone_name":"Disgust"},{"score":0.020325,"tone_id":"fear","tone_name":"Fear"},{"score":0.500012,"tone_id":"joy","tone_name":"Joy"},{"score":0.214145,"tone_id":"sadness","tone_name":"Sadness"}],"category_id":"emotion_tone","category_name":"Emotion Tone"}]},{"sentence_id":1,"text":"Thou art more lovely and more temperate: Rough winds do shake the darling buds of May, and summer's lease hath all too short a date: Sometimes too hot the eye of heaven shines And often is his gold complexion dimmed; And every fair from fair sometime declines, By chance or nature's changing course untrimmed; But thy eternal summer shall not fade Nor lose possession of that fair thou owest; Nor shall Death brag thou wanderest in his shade, When in eternal lines to time thou growest: So long as men can breathe or eyes can see, So long lives this and this gives life to thee.","input_from":40,"input_to":618,"tone_categories":[{"tones":[{"score":0.013243,"tone_id":"anger","tone_name":"Anger"},{"score":0.024489,"tone_id":"disgust","tone_name":"Disgust"},{"score":0.075459,"tone_id":"fear","tone_name":"Fear"},{"score":0.813815,"tone_id":"joy","tone_name":"Joy"},{"score":0.091195,"tone_id":"sadness","tone_name":"Sadness"}],"category_id":"emotion_tone","category_name":"Emotion Tone"}]}]}